mpide/__init__.py
mpide/ide.py
mpide/mpide.css
mpide/py.typed
mpide/target/__init__.py
mpide/target/mpide/misc.py
mpide/target/mpide/setup_ramdisk.py
mpide/utils.py
mpide-0.1.0.dist-info/METADATA
mpide-0.1.0.dist-info/WHEEL
mpide-0.1.0.dist-info/entry_points.txt
mpide-0.1.0.dist-info/RECORD
